<?xml version="1.0" encoding="UTF-8"?>

<esheet>

	<filename><![CDATA[pyb_005_001_003_MG.xml]]></filename>

	<creatorID><![CDATA[MG]]></creatorID>

	<kapitelNrTxt>5</kapitelNrTxt>

	<abschnittNrTxt>1</abschnittNrTxt>

	<beispielNrTxt>3</beispielNrTxt>

	<curDifficulty>1</curDifficulty>

	<tasktitle><![CDATA[Funktionsargumente]]></tasktitle>

	<orientedCommand><![CDATA[]]></orientedCommand>

	<aufgabeStartText><![CDATA[Machen Sie sich damit vertraut, Funktionen als Argumente zu &uuml;bergeben.]]></aufgabeStartText>

	<codelines>
		<line><![CDATA[>>> def halb_addierer(f, x):  ]]></line>
		<line><![CDATA[...     return f(x) + x/2                      ]]></line>
		<line><![CDATA[...]]></line>
		<line><![CDATA[>>> def quadrierer(x):        ]]></line>
		<line><![CDATA[...     return x*x]]></line>
		<line><![CDATA[...                             ]]></line>
		<line><![CDATA[>>> gap;000(gap;001, 5) ]]></line>
		<line><![CDATA[gap;002]]></line>
		<line><![CDATA[>>>]]></line>
	</codelines>

	<numberCodelines><![CDATA[codelines.length]]></numberCodelines>

	<erlaeuterungText><![CDATA[]]></erlaeuterungText>

	<gapFillings>
		<gap>
			<filling><![CDATA[halb_addierer]]></filling>
		</gap>
		<gap>
			<filling><![CDATA[quadrierer]]></filling>
		</gap>
		<gap>
			<filling><![CDATA[27.5]]></filling>
		</gap>
	</gapFillings>

	<posFeedbacks>
		<gap>
			<posFeedback><![CDATA[]]></posFeedback>
		</gap>
		<gap>
			<posFeedback><![CDATA[]]></posFeedback>
		</gap>
		<gap>
			<posFeedback><![CDATA[]]></posFeedback>
		</gap>
	</posFeedbacks>

	<negFeedbacks>
		<gap>
		</gap>
		<gap>
		</gap>
		<gap>
		</gap>
	</negFeedbacks>

	<unspecificNegFeedbacks>
		<gap>
			<unspecificNegFeedback><![CDATA[]]></unspecificNegFeedback>
		</gap>
		<gap>
			<unspecificNegFeedback><![CDATA[]]></unspecificNegFeedback>
		</gap>
		<gap>
			<unspecificNegFeedback><![CDATA[]]></unspecificNegFeedback>
		</gap>
	</unspecificNegFeedbacks>

	<possibleGapPositions>
		<combination>
			<gapSelection>0</gapSelection>
			<gapSelection>1</gapSelection>
			<gapSelection>0</gapSelection>
		</combination>
		<combination>
			<gapSelection>1</gapSelection>
			<gapSelection>0</gapSelection>
			<gapSelection>0</gapSelection>
		</combination>
		<combination>
			<gapSelection>0</gapSelection>
			<gapSelection>0</gapSelection>
			<gapSelection>1</gapSelection>
		</combination>
	</possibleGapPositions>

	<gapLineNumbers>
		<lineNumber>7</lineNumber>
		<lineNumber>7</lineNumber>
		<lineNumber>8</lineNumber>
	</gapLineNumbers>

	<gapStartPositions>
		<startPosition>5</startPosition>
		<startPosition>19</startPosition>
		<startPosition>1</startPosition>
	</gapStartPositions>

	<gapEndPositions>
		<endPosition>17</endPosition>
		<endPosition>28</endPosition>
		<endPosition>4</endPosition>
	</gapEndPositions>

</esheet>